just_three_papers-1.0.0.dist-info/licenses/LICENSE
just_three_papers-1.0.0.dist-info/licenses/LICENSE_DOCS
just_three_papers-1.0.0.dist-info/licenses/LICENSE_OVERVIEW.md
tpocm/__init__.py
tpocm/core.py
just_three_papers-1.0.0.dist-info/METADATA
just_three_papers-1.0.0.dist-info/WHEEL
just_three_papers-1.0.0.dist-info/top_level.txt
just_three_papers-1.0.0.dist-info/RECORD
