Metadata-Version: 2.4
Name: just_three_papers
Version: 1.0.0
Summary: Tri-Planar Orthogonal Complex Mapping Library
Author: Nur Rohmat Hidayatulloh
Author-email: eroscupd@gmail.com
Classifier: Programming Language :: Python :: 3
Classifier: License :: OSI Approved :: GNU General Public License v3 (GPLv3)
Classifier: Operating System :: OS Independent
Classifier: Topic :: Scientific/Engineering :: Mathematics
Requires-Python: >=3.8
License-File: LICENSE
License-File: LICENSE_DOCS
License-File: LICENSE_OVERVIEW.md
Dynamic: author
Dynamic: author-email
Dynamic: classifier
Dynamic: license-file
Dynamic: requires-python
Dynamic: summary
